Workbook

Sheet Параметры
A1: Параметры семейного бюджета
A3: Параметр | B3: Значение | C3: Срок / день | D3: Источник
A4: Зарплата 1 — часть 1 | B4: 35000 | C4: 5 число | D4: Данные пользователя
A5: Зарплата 2 — часть 2 | B5: 43000 | C5: 10 число | D5: Данные пользователя
A6: Зарплата 1 — часть 2 | B6: 65000 | C6: 20 число | D6: Данные пользователя
A7: Зарплата 2 — часть 1 | B7: 17000 | C7: 25 число | D7: Данные пользователя
A8: Ипотека | B8: 45000 | C8: 18 число | D8: Данные пользователя
A9: Коммунальные услуги | B9: 8000 | C9: 14 число | D9: Данные пользователя
A10: Еда | B10: 30000 | C10: в месяц | D10: Данные пользователя
A11: Билеты в отпуск | B11: 100000 | C11: до 01.02.2027 | D11: Данные пользователя
A12: Сам отпуск | B12: 100000 | C12: до 01.04.2027 | D12: Данные пользователя
A14: Важно: 35 000 ₽, полученные 5 октября 2026 года, считаются полностью доступными и включены в план. Они не добавляются второй раз как отдельный стартовый остаток.
A16: Расчёт | B16: Сумма
A17: Доход в месяц | B17: =SUM(B4:B7) -> 160000
A18: Обязательные расходы в месяц | B18: =SUM(B8:B10) -> 83000
A19: Свободно до накоплений | B19: =B17-B18 -> 77000

Sheet План по датам
A1: Сколько откладывать с каждого поступления + трекер выполнения
A3: Дата | B3: Поступление | C3: На ипотеку | D3: На ЖКУ | E3: На еду | F3: На билеты | G3: На отпуск | H3: Свободный резерв | I3: Комментарий | J3: Статус | K3: План отложить | L3: Факт отложено | M3: Факт на билеты | N3: Факт на отпуск | O3: Выполнение
A4: 46300 | B4: 35000 | C4: 15000 | D4: 8000 | E4: 5000 | F4: 4000 | G4: 3000 | H4: 0 | I4: Уже получено и полностью осталось; распределить сейчас | J4: Отложил | K4: =C4+D4+F4+G4 -> 30000 | L4: =IF(J4="Отложил",K4,0) -> 30000 | M4: =IF(J4="Отложил",F4,0) -> 4000 | N4: =IF(J4="Отложил",G4,0) -> 3000 | O4: =IF(J4="Отложил",1,0) -> 1
A5: 46305 | B5: 43000 | C5: 30000 | D5: 0 | E5: 5000 | F5: 6000 | G5: 2000 | H5: 0 | I5: После этого к 14-му ЖКУ и к 18-му ипотека полностью собраны | K5: =C5+D5+F5+G5 -> 38000 | L5: =IF(J5="Отложил",K5,0) -> 0 | M5: =IF(J5="Отложил",F5,0) -> 0 | N5: =IF(J5="Отложил",G5,0) -> 0 | O5: =IF(J5="Отложил",1,0) -> 0
A6: 46315 | B6: 65000 | C6: 0 | D6: 0 | E6: 10000 | F6: 10000 | G6: 10000 | H6: 35000 | I6: Основное накопление после обязательных платежей | K6: =C6+D6+F6+G6 -> 20000 | L6: =IF(J6="Отложил",K6,0) -> 0 | M6: =IF(J6="Отложил",F6,0) -> 0 | N6: =IF(J6="Отложил",G6,0) -> 0 | O6: =IF(J6="Отложил",1,0) -> 0
A7: 46320 | B7: 17000 | C7: 0 | D7: 0 | E7: 10000 | F7: 5000 | G7: 2000 | H7: 0 | I7: Закрыть месячный лимит на еду и накопления | K7: =C7+D7+F7+G7 -> 7000 | L7: =IF(J7="Отложил",K7,0) -> 0 | M7: =IF(J7="Отложил",F7,0) -> 0 | N7: =IF(J7="Отложил",G7,0) -> 0 | O7: =IF(J7="Отложил",1,0) -> 0
A8: 46331 | B8: 35000 | C8: 15000 | D8: 8000 | E8: 5000 | F8: 4000 | G8: 3000 | H8: 0 | I8: Сразу зарезервировать ЖКУ и часть ипотеки | K8: =C8+D8+F8+G8 -> 30000 | L8: =IF(J8="Отложил",K8,0) -> 0 | M8: =IF(J8="Отложил",F8,0) -> 0 | N8: =IF(J8="Отложил",G8,0) -> 0 | O8: =IF(J8="Отложил",1,0) -> 0
A9: 46336 | B9: 43000 | C9: 30000 | D9: 0 | E9: 5000 | F9: 6000 | G9: 2000 | H9: 0 | I9: После этого к 14-му ЖКУ и к 18-му ипотека полностью собраны | K9: =C9+D9+F9+G9 -> 38000 | L9: =IF(J9="Отложил",K9,0) -> 0 | M9: =IF(J9="Отложил",F9,0) -> 0 | N9: =IF(J9="Отложил",G9,0) -> 0 | O9: =IF(J9="Отложил",1,0) -> 0
A10: 46346 | B10: 65000 | C10: 0 | D10: 0 | E10: 10000 | F10: 10000 | G10: 10000 | H10: 35000 | I10: Основное накопление после обязательных платежей | K10: =C10+D10+F10+G10 -> 20000 | L10: =IF(J10="Отложил",K10,0) -> 0 | M10: =IF(J10="Отложил",F10,0) -> 0 | N10: =IF(J10="Отложил",G10,0) -> 0 | O10: =IF(J10="Отложил",1,0) -> 0
A11: 46351 | B11: 17000 | C11: 0 | D11: 0 | E11: 10000 | F11: 5000 | G11: 2000 | H11: 0 | I11: Закрыть месячный лимит на еду и накопления | K11: =C11+D11+F11+G11 -> 7000 | L11: =IF(J11="Отложил",K11,0) -> 0 | M11: =IF(J11="Отложил",F11,0) -> 0 | N11: =IF(J11="Отложил",G11,0) -> 0 | O11: =IF(J11="Отложил",1,0) -> 0
A12: 46361 | B12: 35000 | C12: 15000 | D12: 8000 | E12: 5000 | F12: 4000 | G12: 3000 | H12: 0 | I12: Сразу зарезервировать ЖКУ и часть ипотеки | K12: =C12+D12+F12+G12 -> 30000 | L12: =IF(J12="Отложил",K12,0) -> 0 | M12: =IF(J12="Отложил",F12,0) -> 0 | N12: =IF(J12="Отложил",G12,0) -> 0 | O12: =IF(J12="Отложил",1,0) -> 0
A13: 46366 | B13: 43000 | C13: 30000 | D13: 0 | E13: 5000 | F13: 6000 | G13: 2000 | H13: 0 | I13: После этого к 14-му ЖКУ и к 18-му ипотека полностью собраны | K13: =C13+D13+F13+G13 -> 38000 | L13: =IF(J13="Отложил",K13,0) -> 0 | M13: =IF(J13="Отложил",F13,0) -> 0 | N13: =IF(J13="Отложил",G13,0) -> 0 | O13: =IF(J13="Отложил",1,0) -> 0
A14: 46376 | B14: 65000 | C14: 0 | D14: 0 | E14: 10000 | F14: 10000 | G14: 10000 | H14: 35000 | I14: Основное накопление после обязательных платежей | K14: =C14+D14+F14+G14 -> 20000 | L14: =IF(J14="Отложил",K14,0) -> 0 | M14: =IF(J14="Отложил",F14,0) -> 0 | N14: =IF(J14="Отложил",G14,0) -> 0 | O14: =IF(J14="Отложил",1,0) -> 0
A15: 46381 | B15: 17000 | C15: 0 | D15: 0 | E15: 10000 | F15: 5000 | G15: 2000 | H15: 0 | I15: Закрыть месячный лимит на еду и накопления | K15: =C15+D15+F15+G15 -> 7000 | L15: =IF(J15="Отложил",K15,0) -> 0 | M15: =IF(J15="Отложил",F15,0) -> 0 | N15: =IF(J15="Отложил",G15,0) -> 0 | O15: =IF(J15="Отложил",1,0) -> 0
A16: 46392 | B16: 35000 | C16: 15000 | D16: 8000 | E16: 5000 | F16: 4000 | G16: 3000 | H16: 0 | I16: Сразу зарезервировать ЖКУ и часть ипотеки | K16: =C16+D16+F16+G16 -> 30000 | L16: =IF(J16="Отложил",K16,0) -> 0 | M16: =IF(J16="Отложил",F16,0) -> 0 | N16: =IF(J16="Отложил",G16,0) -> 0 | O16: =IF(J16="Отложил",1,0) -> 0
... A27: 46471 | B27: 17000 | C27: 0 | D27: 0 | E27: 10000 | F27: 0 | G27: 2000 | H27: 5000 | I27: Закрыть месячный лимит на еду и накопления | K27: =C27+D27+F27+G27 -> 2000 | L27: =IF(J27="Отложил",K27,0) -> 0 | M27: =IF(J27="Отложил",F27,0) -> 0 | N27: =IF(J27="Отложил",G27,0) -> 0 | O27: =IF(J27="Отложил",1,0) -> 0

Sheet Сводка
A1: Сводка бюджета и контроль целей | L1: Прогресс накоплений
A3: Месяц | B3: Доход | C3: Ипотека | D3: ЖКУ | E3: Еда | F3: Билеты | G3: Отпуск | H3: Свободный резерв | I3: Накоплено на билеты | J3: Накоплено на отпуск | L3: Цель | M3: План | N3: Фактически | O3: Прогресс
A4: Октябрь 2026 | B4: =SUM('План по датам'!B4:B7) -> 160000 | C4: =SUM('План по датам'!C4:C7) -> 45000 | D4: =SUM('План по датам'!D4:D7) -> 8000 | E4: =SUM('План по датам'!E4:E7) -> 30000 | F4: =SUM('План по датам'!F4:F7) -> 25000 | G4: =SUM('План по датам'!G4:G7) -> 17000 | H4: =SUM('План по датам'!H4:H7) -> 35000 | I4: =F4 -> 25000 | J4: =G4 -> 17000 | L4: Билеты | M4: 100000 | N4: =SUM('План по датам'!M4:M27) -> 4000 | O4: =MIN(N4/M4,1) -> 0.04
A5: Ноябрь 2026 | B5: =SUM('План по датам'!B8:B11) -> 160000 | C5: =SUM('План по датам'!C8:C11) -> 45000 | D5: =SUM('План по датам'!D8:D11) -> 8000 | E5: =SUM('План по датам'!E8:E11) -> 30000 | F5: =SUM('План по датам'!F8:F11) -> 25000 | G5: =SUM('План по датам'!G8:G11) -> 17000 | H5: =SUM('План по датам'!H8:H11) -> 35000 | I5: =I4+F5 -> 50000 | J5: =J4+G5 -> 34000 | L5: Отпуск | M5: 100000 | N5: =SUM('План по датам'!N4:N27) -> 3000 | O5: =MIN(N5/M5,1) -> 0.03
A6: Декабрь 2026 | B6: =SUM('План по датам'!B12:B15) -> 160000 | C6: =SUM('План по датам'!C12:C15) -> 45000 | D6: =SUM('План по датам'!D12:D15) -> 8000 | E6: =SUM('План по датам'!E12:E15) -> 30000 | F6: =SUM('План по датам'!F12:F15) -> 25000 | G6: =SUM('План по датам'!G12:G15) -> 17000 | H6: =SUM('План по датам'!H12:H15) -> 35000 | I6: =I5+F6 -> 75000 | J6: =J5+G6 -> 51000 | L6: Всего | M6: 200000 | N6: =N4+N5 -> 7000 | O6: =MIN(N6/M6,1) -> 0.035
A7: Январь 2027 | B7: =SUM('План по датам'!B16:B19) -> 160000 | C7: =SUM('План по датам'!C16:C19) -> 45000 | D7: =SUM('План по датам'!D16:D19) -> 8000 | E7: =SUM('План по датам'!E16:E19) -> 30000 | F7: =SUM('План по датам'!F16:F19) -> 25000 | G7: =SUM('План по датам'!G16:G19) -> 17000 | H7: =SUM('План по датам'!H16:H19) -> 35000 | I7: =I6+F7 -> 100000 | J7: =J6+G7 -> 68000
A8: Февраль 2027 | B8: =SUM('План по датам'!B20:B23) -> 160000 | C8: =SUM('План по датам'!C20:C23) -> 45000 | D8: =SUM('План по датам'!D20:D23) -> 8000 | E8: =SUM('План по датам'!E20:E23) -> 30000 | F8: =SUM('План по датам'!F20:F23) -> 0 | G8: =SUM('План по датам'!G20:G23) -> 16000 | H8: =SUM('План по датам'!H20:H23) -> 61000 | I8: =I7+F8 -> 100000 | J8: =J7+G8 -> 84000
A9: Март 2027 | B9: =SUM('План по датам'!B24:B27) -> 160000 | C9: =SUM('План по датам'!C24:C27) -> 45000 | D9: =SUM('План по датам'!D24:D27) -> 8000 | E9: =SUM('План по датам'!E24:E27) -> 30000 | F9: =SUM('План по датам'!F24:F27) -> 0 | G9: =SUM('План по датам'!G24:G27) -> 16000 | H9: =SUM('План по датам'!H24:H27) -> 61000 | I9: =I8+F9 -> 100000 | J9: =J8+G9 -> 100000 | L9: Выполнение плана по датам
L10: Отмечено «Отложил» | M10: Всего поступлений | N10: Выполнение
L11: =COUNTIF('План по датам'!J4:J27,"Отложил") -> 1 | M11: 24 | N11: =L11/M11 -> 0.041666667
A12: Контроль | B12: Цель | C12: Факт | D12: Статус | F12: Итог по плану
A13: ЖКУ к 14 числу | B13: 8000 | C13: ='План по датам'!D4+'План по датам'!D5 -> 8000 | D13: =IF(C13>=B13,"Выполнено","Не хватает") -> Выполнено | F13: Билеты: 100 000 ₽ будут собраны к 25 января 2027 г. | L13: Как пользоваться: на листе «План по датам» в колонке «Статус» выбирайте «Отложил» после того, как распределили деньги. Шкалы прогресса обновятся автоматически.
A14: Ипотека к 18 числу | B14: 45000 | C14: ='План по датам'!C4+'План по датам'!C5 -> 45000 | D14: =IF(C14>=B14,"Выполнено","Не хватает") -> Выполнено | F14: Отпуск: 100 000 ₽ будут собраны к 25 марта 2027 г.
A15: Билеты к 01.02.2027 | B15: 100000 | C15: =I7 -> 100000 | D15: =IF(C15>=B15,"Выполнено","Не хватает") -> Выполнено | F15: С октября по январь свободный резерв: 35 000 ₽ в месяц.
A16: Отпуск к 01.04.2027 | B16: 100000 | C16: =J9 -> 100000 | D16: =IF(C16>=B16,"Выполнено","Не хватает") -> Выполнено | F16: В феврале и марте свободный резерв: 61 000 ₽ в месяц.
